stdlibby_py/__init__.py
stdlibby_py/algorithms.py
stdlibby_py/api.py
stdlibby_py/cly.py
stdlibby_py/dt.py
stdlibby_py/errors.py
stdlibby_py/facets.py
stdlibby_py/html.py
stdlibby_py/logger.py
stdlibby_py/main.py
stdlibby_py/ndjson.py
stdlibby_py/sockets.py
stdlibby_py/sqlite.py
stdlibby_py/utils.py
stdlibby_py-0.5.17.dist-info/METADATA
stdlibby_py-0.5.17.dist-info/WHEEL
stdlibby_py-0.5.17.dist-info/RECORD
